mikoblocks/__init__.py
mikoblocks/utils.py
mikoblocks-0.1.2.dist-info/LICENSE
mikoblocks-0.1.2.dist-info/METADATA
mikoblocks-0.1.2.dist-info/WHEEL
mikoblocks-0.1.2.dist-info/top_level.txt
mikoblocks-0.1.2.dist-info/RECORD
