Metadata-Version: 2.1
Name: mikoblocks
Version: 0.1.2
Summary: Mikoblocks is a minimal library to programmatically generate html.
Author-email: Alex Stevovich <alex.stevovich@gmail.com>
License: Copyright (c) 2018 Alex Stevovich
Classifier: Development Status :: 4 - Beta
Classifier: Intended Audience :: Developers
Classifier: License :: Other/Proprietary License
Classifier: Operating System :: OS Independent
Classifier: Programming Language :: Python :: 3
Classifier: Programming Language :: Python :: 3.8
Classifier: Programming Language :: Python :: 3.9
Classifier: Programming Language :: Python :: 3.10
License-File: LICENSE
